Metadata-Version: 1.1
Name: django-daterange-filter
Version: 0.2.0
Summary: Allow to filter by a custom date range on the Django Admin
Home-page: http://github.com/tzulberti/django-datefilterspec
Author: Tomas Zulberti
Author-email: tzulberti@gmail.com
License: License :: OSI Approved :: BSD License
Keywords: django admin,django date range
Platform: UNKNOWN
Classifier: Development Status :: 5 - Production/Stable
Classifier: Intended Audience :: Developers
Classifier: License :: OSI Approved :: BSD License
Classifier: Framework :: Django
Classifier: Programming Language :: Python
Classifier: Programming Language :: Python :: 2.4
Classifier: Programming Language :: Python :: 2.5
Classifier: Programming Language :: Python :: 2.6
Classifier: Programming Language :: Python :: 2.7
Classifier: Topic :: Software Development :: Libraries :: Python Modules
Classifier: Topic :: Internet :: WWW/HTTP :: WSGI
Classifier: Topic :: Software Development :: Libraries :: Application Frameworks
Classifier: Topic :: Internet :: WWW/HTTP :: Dynamic Content
Classifier: Environment :: Web Environment
Classifier: Operating System :: OS Independent
